LICENSE-MIT
MANIFEST.in
README.md
setup.py
bower_components/bootstrap/.bower.json
bower_components/bootstrap/Gruntfile.js
bower_components/bootstrap/LICENSE
bower_components/bootstrap/README.md
bower_components/bootstrap/bower.json
bower_components/bootstrap/package.js
bower_components/bootstrap/package.json
bower_components/bootstrap/dist/css/bootstrap-theme.css
bower_components/bootstrap/dist/css/bootstrap-theme.css.map
bower_components/bootstrap/dist/css/bootstrap-theme.min.css
bower_components/bootstrap/dist/css/bootstrap.css
bower_components/bootstrap/dist/css/bootstrap.css.map
bower_components/bootstrap/dist/css/bootstrap.min.css
bower_components/bootstrap/dist/fonts/glyphicons-halflings-regular.eot
bower_components/bootstrap/dist/fonts/glyphicons-halflings-regular.svg
bower_components/bootstrap/dist/fonts/glyphicons-halflings-regular.ttf
bower_components/bootstrap/dist/fonts/glyphicons-halflings-regular.woff
bower_components/bootstrap/dist/fonts/glyphicons-halflings-regular.woff2
bower_components/bootstrap/dist/js/bootstrap.js
bower_components/bootstrap/dist/js/bootstrap.min.js
bower_components/bootstrap/dist/js/npm.js
bower_components/bootstrap/fonts/glyphicons-halflings-regular.eot
bower_components/bootstrap/fonts/glyphicons-halflings-regular.svg
bower_components/bootstrap/fonts/glyphicons-halflings-regular.ttf
bower_components/bootstrap/fonts/glyphicons-halflings-regular.woff
bower_components/bootstrap/fonts/glyphicons-halflings-regular.woff2
bower_components/bootstrap/grunt/.jshintrc
bower_components/bootstrap/grunt/bs-commonjs-generator.js
bower_components/bootstrap/grunt/bs-glyphicons-data-generator.js
bower_components/bootstrap/grunt/bs-lessdoc-parser.js
bower_components/bootstrap/grunt/bs-raw-files-generator.js
bower_components/bootstrap/grunt/configBridge.json
bower_components/bootstrap/grunt/sauce_browsers.yml
bower_components/bootstrap/js/.jscsrc
bower_components/bootstrap/js/.jshintrc
bower_components/bootstrap/js/affix.js
tocka_djangocms_cascade.egg-info/PKG-INFO
tocka_djangocms_cascade.egg-info/SOURCES.txt
tocka_djangocms_cascade.egg-info/dependency_links.txt
tocka_djangocms_cascade.egg-info/not-zip-safe
tocka_djangocms_cascade.egg-info/requires.txt
tocka_djangocms_cascade.egg-info/top_level.txt