Metadata-Version: 1.1
Name: tocka-djangocms-cascade
Version: 0.6.0.1
Summary: Fork of djangocms-cascade
Home-page: https://github.com/frnhr/djangocms-cascade
Author: Fran Hrzenjak
Author-email: fran@changeset.hr
License: LICENSE-MIT
Platform: OS Independent
Classifier: Development Status :: 4 - Beta
Classifier: Environment :: Web Environment
Classifier: Framework :: Django
Classifier: Intended Audience :: Developers
Classifier: License :: OSI Approved :: MIT License
Classifier: Operating System :: OS Independent
Classifier: Programming Language :: Python
Classifier: Topic :: Internet :: WWW/HTTP :: Dynamic Content
Classifier: Programming Language :: Python :: 2.7
Classifier: Programming Language :: Python :: 3.3
